forte.tweepy-0.0.3-py3.7-nspkg.pth
fortex/tweepy/__init__.py
fortex/tweepy/twittersearch_processor.py
forte.tweepy-0.0.3.dist-info/METADATA
forte.tweepy-0.0.3.dist-info/WHEEL
forte.tweepy-0.0.3.dist-info/namespace_packages.txt
forte.tweepy-0.0.3.dist-info/top_level.txt
forte.tweepy-0.0.3.dist-info/RECORD
